examples/__init__.py
examples/sandbox_gui.py
model_explain/__init__.py
model_explain/cli.py
model_explain/explainers/__init__.py
model_explain/explainers/counterfactual.py
model_explain/explainers/fairness.py
model_explain/explainers/grad_cam.py
model_explain/explainers/integrated_gradients.py
model_explain/explainers/lime_explainer.py
model_explain/explainers/model_comparison.py
model_explain/explainers/nl_summary.py
model_explain/explainers/obero.py
model_explain/explainers/permutation_importance.py
model_explain/explainers/saliency_maps.py
model_explain/explainers/shap_explainer.py
model_explain/explainers/summary.py
model_explain/explainers/surrogate.py
model_explain/utils/__init__.py
model_explain/utils/explainability_score.py
model_explain/utils/heatmap_overlay.py
model_explain/utils/model_loader.py
model_explain/visualizations/__init__.py
model_explain/visualizations/feature_importance_plot.py
model_explain/visualizations/interactive.py
model_explain-0.4.0.dist-info/licenses/LICENSE
model_explain-0.4.0.dist-info/METADATA
model_explain-0.4.0.dist-info/WHEEL
model_explain-0.4.0.dist-info/entry_points.txt
model_explain-0.4.0.dist-info/top_level.txt
model_explain-0.4.0.dist-info/RECORD
