Metadata-Version: 2.4
Name: model_explain
Version: 0.4.0
Summary: A unified Python package for interpreting and explaining machine learning and deep learning models, including feature attention mechanisms. Supports popular explanation techniques such as LIME, SHAP, Grad-CAM, permutation importance, and saliency maps. Provides a consistent interface for tabular, image, and other data types, enabling model transparency and interpretability.
Home-page: https://github.com/vaibhav-k/model_explain
Author: Vaibhav Kulshrestha
Author-email: vaibhav1kulshrestha@gmail.com
Project-URL: Source, https://github.com/vaibhav-k/model_explain
Project-URL: Tracker, https://github.com/vaibhav-k/model_explain/issues
Requires-Python: >=3.8
License-File: LICENSE
Requires-Dist: torch<3.0.0,>=2.0.0
Requires-Dist: plotly<6.0.0,>=5.0.0
Requires-Dist: fairlearn<0.11.0,>=0.8.0
Requires-Dist: dice-ml<1.0,>=0.9
Requires-Dist: numpy<2.0.0,>=1.20.0
Requires-Dist: pandas<2.0.0,>=1.3.0
Requires-Dist: scikit-learn<2.0.0,>=1.0.0
Requires-Dist: shap<1.0.0,>=0.41.0
Requires-Dist: lime<0.3.0,>=0.2.0.1
Requires-Dist: streamlit<2.0.0,>=1.0.0
Requires-Dist: xgboost<2.0.0,>=1.5.0
Requires-Dist: joblib<2.0.0,>=1.0.0
Requires-Dist: matplotlib<4.0.0,>=3.4.0
Requires-Dist: seaborn<1.0.0,>=0.11.0
Dynamic: author
Dynamic: author-email
Dynamic: description
Dynamic: description-content-type
Dynamic: home-page
Dynamic: license-file
Dynamic: project-url
Dynamic: requires-dist
Dynamic: requires-python
Dynamic: summary
